awslambdaric-stubs/__init__.pyi
awslambdaric-stubs/lambda_context.pyi
awslambdaric_stubs-0.1.0.dist-info/LICENSE
awslambdaric_stubs-0.1.0.dist-info/METADATA
awslambdaric_stubs-0.1.0.dist-info/WHEEL
awslambdaric_stubs-0.1.0.dist-info/top_level.txt
awslambdaric_stubs-0.1.0.dist-info/RECORD
