Metadata-Version: 2.1
Name: awslambdaric-stubs
Version: 0.1.0
Summary: Stubs for AWS Lambda Python Runtime Interface Client(awslambdaric)
Home-page: https://github.com/toidi/awslambdaric-stubs
Author: Eduard Iskandarov
Author-email: eduard.iskandarov@yandex.ru
License: MIT License
Platform: UNKNOWN
Classifier: Development Status :: 3 - Alpha
Classifier: Programming Language :: Python :: 3
